gpd/__init__.py
gpd/cache/__init__.py
gpd/cache/dependent_cache.py
gpd/dependent_downloader.py
gpd/dependents_stats.py
gpd/models/__init__.py
gpd/models/dependent.py
gpd/models/dependent_key.py
gpd/parsers/__init__.py
gpd/parsers/dependent_parser.py
gpd/parsers/table_page_parser.py
gpd/runner.py
gpd/settings.py
gpd-1.1.1.dist-info/entry_points.txt
gpd-1.1.1.dist-info/LICENSE
gpd-1.1.1.dist-info/WHEEL
gpd-1.1.1.dist-info/METADATA
gpd-1.1.1.dist-info/RECORD
