Metadata-Version: 2.1
Name: gpd
Version: 1.1.1
Summary: Get a list of popular projects that use a library.
Home-page: https://github.com/MislavJaksic/get-popular-dependents
License: MIT
Author: Mislav Jaksic
Author-email: jaksicmislav@gmail.com
Requires-Python: >=3.8,<4.0
Classifier: License :: OSI Approved :: MIT License
Classifier: Programming Language :: Python :: 3
Classifier: Programming Language :: Python :: 3.10
Classifier: Programming Language :: Python :: 3.8
Classifier: Programming Language :: Python :: 3.9
Requires-Dist: bs4 (>=0.0.1,<0.0.2)
Requires-Dist: diskcache (>=5.4.0,<6.0.0)
Requires-Dist: loguru (>=0.6.0,<0.7.0)
Requires-Dist: pydantic (>=1.9.1,<2.0.0)
Requires-Dist: requests (>=2.27.1,<3.0.0)
Requires-Dist: tabulate (>=0.8.9,<0.9.0)
Requires-Dist: tqdm (>=4.64.0,<5.0.0)
Project-URL: Documentation, https://github.com/MislavJaksic/get-popular-dependents
Project-URL: Repository, https://github.com/MislavJaksic/get-popular-dependents
